traces/__init__.py
traces/decorators.py
traces/eventseries.py
traces/histogram.py
traces/infinity.py
traces/operations.py
traces/plot.py
traces/timeseries.py
traces/utils.py
traces-0.6.4.dist-info/LICENSE
traces-0.6.4.dist-info/METADATA
traces-0.6.4.dist-info/WHEEL
traces-0.6.4.dist-info/RECORD
