Metadata-Version: 2.1
Name: traces
Version: 0.6.4
Summary: A Python library for unevenly-spaced time series analysis
Home-page: https://github.com/stringertheory/traces
Author: Mike Stringer
Author-email: mike.stringer.internet@gmail.com
Requires-Python: >=3.8,<4.0
Classifier: Programming Language :: Python :: 3
Classifier: Programming Language :: Python :: 3.8
Classifier: Programming Language :: Python :: 3.9
Classifier: Programming Language :: Python :: 3.10
Classifier: Programming Language :: Python :: 3.11
Classifier: Programming Language :: Python :: 3.12
Requires-Dist: sortedcontainers (>=2.4.0,<3.0.0)
Project-URL: Documentation, https://stringertheory.github.io/traces/
Project-URL: Repository, https://github.com/stringertheory/traces
